st_pydantic/__init__.py
st_pydantic/_about.py
st_pydantic/py.typed
st_pydantic/schema_utils.py
st_pydantic/settings.py
st_pydantic/types.py
st_pydantic/ui_renderer.py
st_pydantic-0.3.1.dist-info/LICENSE
st_pydantic-0.3.1.dist-info/METADATA
st_pydantic-0.3.1.dist-info/WHEEL
st_pydantic-0.3.1.dist-info/RECORD
