Metadata-Version: 2.1
Name: st-pydantic
Version: 0.3.1
Summary: Auto-generate Streamlit UI from Pydantic models and dataclasses.
Home-page: https://github.com/MatanRubin/st-pydantic/
License: MIT
Keywords: streamlit,pydantic,dataclasses,ui,forms,validation,schema
Author: Lukas Masuch
Author-email: lukas.masuch@gmail.com
Maintainer: Matan Rubin
Maintainer-email: matan.rubin@solaredge.com
Requires-Python: >=3.10,<4.0
Classifier: Development Status :: 4 - Beta
Classifier: Intended Audience :: Developers
Classifier: Intended Audience :: Information Technology
Classifier: Intended Audience :: Science/Research
Classifier: License :: OSI Approved :: MIT License
Classifier: Natural Language :: English
Classifier: Operating System :: OS Independent
Classifier: Programming Language :: Python :: 3
Classifier: Programming Language :: Python :: 3.10
Classifier: Programming Language :: Python :: 3.11
Classifier: Programming Language :: Python :: 3.12
Classifier: Programming Language :: Python :: 3 :: Only
Classifier: Programming Language :: Python :: 3.7
Classifier: Programming Language :: Python :: 3.8
Classifier: Programming Language :: Python :: 3.9
Classifier: Programming Language :: Python :: Implementation :: CPython
Classifier: Programming Language :: Python :: Implementation :: PyPy
Classifier: Topic :: Scientific/Engineering
Classifier: Topic :: Scientific/Engineering :: Artificial Intelligence
Classifier: Topic :: Software Development
Classifier: Topic :: Software Development :: Libraries
Classifier: Topic :: Software Development :: Libraries :: Python Modules
Classifier: Topic :: Utilities
Requires-Dist: pydantic (>=2.0.0,<3.0.0)
Requires-Dist: streamlit (>=1.14.0,<2.0.0)
Project-URL: Repository, https://github.com/MatanRubin/st-pydantic
